curlIO.cpython-311-x86_64-linux-gnu.so
curlIO-0.1.2.dist-info/METADATA
curlIO-0.1.2.dist-info/WHEEL
curlIO-0.1.2.dist-info/top_level.txt
curlIO-0.1.2.dist-info/RECORD
curlIO.libs/libssh-c11d285b.so.4.8.7
curlIO.libs/libssl-52849bc7.so.1.1.1k
curlIO.libs/libbrotlidec-811d1be3.so.1.0.6
curlIO.libs/libidn2-2f4a5893.so.0.3.6
curlIO.libs/libkrb5-d5e439bf.so.3.3
curlIO.libs/libcurl-bca368c1.so.4.5.0
curlIO.libs/libpsl-99becdd3.so.5.3.1
curlIO.libs/libbrotlicommon-6ce2a53c.so.1.0.6
curlIO.libs/libk5crypto-c7449546.so.3.1
curlIO.libs/libselinux-64a010fa.so.1
curlIO.libs/libgssapi_krb5-134fb67a.so.2.2
curlIO.libs/liblber-2-103042e8.4.so.2.10.9
curlIO.libs/libunistring-05abdd40.so.2.1.0
curlIO.libs/libcrypto-401bea5d.so.1.1.1k
curlIO.libs/libkrb5support-de4617ba.so.0.1
curlIO.libs/libpcre2-8-516f4c9d.so.0.7.1
curlIO.libs/libkeyutils-2777d33d.so.1.6
curlIO.libs/libcom_err-b4375b23.so.2.1
curlIO.libs/libsasl2-7de4d792.so.3.0.0
curlIO.libs/libcrypt-52aca757.so.1.1.0
curlIO.libs/libnghttp2-39367a22.so.14.17.0
curlIO.libs/libldap-2-da21aa92.4.so.2.10.9
