Metadata-Version: 2.1
Name: curlIO
Version: 0.1.2
Summary: genhttpv1 library collection
Home-page: https://github.com/Goychay23/curlIO
Author: Zaman huseynli
Author-email: zamanhuseynli23@gmail.com
Classifier: Programming Language :: Python :: 3
Classifier: Programming Language :: Python :: 3.8
Classifier: Programming Language :: Python :: 3.9
Classifier: Programming Language :: Python :: 3.10
Classifier: Programming Language :: Python :: 3.11
Classifier: Programming Language :: Python :: 3.12
Classifier: License :: OSI Approved :: MIT License
Classifier: Operating System :: OS Independent
